wsnsimpy/__init__.py
wsnsimpy/common.py
wsnsimpy/examples/__init__.py
wsnsimpy/examples/aodv.py
wsnsimpy/examples/clock-demo.py
wsnsimpy/examples/flood.py
wsnsimpy/examples/gossip.py
wsnsimpy/examples/layered-aodv.py
wsnsimpy/examples/layered-flood.py
wsnsimpy/scene.py
wsnsimpy/tkrenderer.py
wsnsimpy/wsnsimpy.py
wsnsimpy/wsnsimpy_tk.py
wsnsimpy-1.0.1.dist-info/LICENSE
wsnsimpy-1.0.1.dist-info/METADATA
wsnsimpy-1.0.1.dist-info/WHEEL
wsnsimpy-1.0.1.dist-info/RECORD
