Metadata-Version: 2.1
Name: wsnsimpy
Version: 1.0.1
Summary: SimPy-based WSN Simulator
Home-page: https://gitlab.com/cjaikaeo/wsnsimpy
License: BSD 2-clause
Author: Chaiporn Jaikaeo
Author-email: chaiporn.j@ku.ac.th
Requires-Python: >=3.6,<4.0
Classifier: License :: Other/Proprietary License
Classifier: Programming Language :: Python :: 3
Classifier: Programming Language :: Python :: 3.6
Classifier: Programming Language :: Python :: 3.7
Classifier: Programming Language :: Python :: 3.8
Classifier: Programming Language :: Python :: 3.9
Classifier: Programming Language :: Python :: 3.10
Classifier: Programming Language :: Python :: 3.11
Classifier: Programming Language :: Python :: 3.12
Requires-Dist: simpy (>=4.0.1,<5.0.0)
